Workbook

Sheet Ramsay (IFRS)
B1: Montant en (MEU) | E1: Indices calcule en (MEU)
B2: 2024 | C2: 2023 | F2: 2024 | G2: 2023 | H2: Variation
A3: Chiffre d affaires | B3: 5006.5 | C3: 4701.5 | E3: BFR | F3: =(B14-B11)-(B15-(B16+B17+B18)) -> -222.6 | G3: =(C14-C11)-(C15-(C16+C17+C18)) -> -199 | H3: =F3-G3 -> -23.6
A4: Achats consommes | B4: 1063.9 | C4: 978.8 | E4: FR | F4: =(B12+B13)-B8 -> -219.4 | G4: =(C12+C13)-C8 -> -126.4 | H4: =F4-G4 -> -93
A5: Excedent brut d exploitation (EBE) | B5: 610.9 | C5: 621.4 | E5: TN | F5: =F4-F3 -> 3.2 | G5: =G4-G3 -> 72.6 | H5: =F5-G5 -> -69.4
A6: Amortissements | B6: 426.7 | C6: 403.2 | E6: DSO | F6: =B10/B3*365 -> 50.100469 | G6: =C10/C3*365 -> 41.814102 | H6: =F6-G6 -> 8.2863675
A7: Resultat Net par Group | B7: -53.9 | C7: 49.4 | E7: DIO | F7: =B9/B4*365 -> 42.88467 | G7: =C9/C4*365 -> 44.077442 | H7: =F7-G7 -> -1.1927722
A8: Actifs non courants | B8: 5428.6 | C8: 5591.6 | E8: DPO | F8: =B19/B4*365 -> 157.06081 | G8: =C19/C4*365 -> 175.97415 | H8: =F8-G8 -> -18.913338
A9: Stocks | B9: 125 | C9: 118.2 | E9: Marge d EBITDA | F9: =B5/B3 -> 0.12202137 | G9: =C5/C3 -> 0.13217058 | H9: =F9-G9 -> -0.010149212
A10: Clients | B10: 687.2 | C10: 538.6 | E10: Taux de conversion | F10: =B20/B5 -> 0.96055001 | G10: =C20/C5 -> 0.96379144 | H10: =F10-G10 -> -0.0032414305
A11: Tresorerie et equivalents | B11: 359 | C11: 352.2 | E11: Capex/Amortissements | F11: =ABS(B21/B6) -> 0.39489102 | G11: =ABS(C21/C6) -> 0.42708333 | H11: =F11-G11 -> -0.032192309
A12: Total Capitaux propres | B12: 1229.7 | C12: 1276.9 | E12: Resultat Net par Group | F12: -53.9 | G12: 49.4 | H12: =F12-G12 -> -103.3
A13: Passifs non courants | B13: 3979.5 | C13: 4188.3
A14: Actifs courants | B14: 1466.6 | C14: 1366.2
A15: Passifs courants | B15: 1686 | C15: 1492.6
A16: Dettes financieres courantes | B16: 104.3 | C16: 58.8
A17: Dettes sur engagements | B17: 6.4 | C17: 7.3
A18: Dettes de location courantes | B18: 245.1 | C18: 213.5
A19: Fournisseurs | B19: 457.8 | C19: 471.9
A20: Flux net generes par l activite | B20: 586.8 | C20: 598.9
A21: Investissements corporels et incorporels(Capex) | B21: -168.5 | C21: -172.2

Sheet AKDITAL
B1: Montant en (MDH)
B2: 2022 | C2: 2023 | D2: 2024 | F2: Indices calcule en (MDH)
A3: Chiffre d affaires | B3: =1034777927/10^6 -> 1034.7779 | C3: =1907329124/10^6 -> 1907.3291 | D3: =2954038793/10^6 -> 2954.0388 | G3: 2022 | H3: 2023 | I3: 2024
A4: Stocks et en-cours | B4: =57093526/10^6 -> 57.093526 | C4: =98819040/10^6 -> 98.81904 | D4: =176555475/10^6 -> 176.55548 | F4: BFR | G4: =B9-B10 -> -343.33501 | H4: =C9-C10 -> -318.6281 | I4: =D9-D10 -> -388.47571
A5: Clients et comptes rattachés | B5: =384593504/10^6 -> 384.5935 | C5: =699135133/10^6 -> 699.13513 | D5: =975688986/10^6 -> 975.68899 | F5: FR | G5: =(B12+B13+B14+B15)-B16 -> -94.555412 | H5: =(C12+C13+C14+C15)-C16 -> -230.72524 | I5: =(D12+D13+D14+D15)-D16 -> 1373.925
A6: Autres créances | B6: =244704415/10^6 -> 244.70442 | C6: =160233517/10^6 -> 160.23352 | D6: =189173473/10^6 -> 189.17347 | F6: TN | G6: =G5-G4 -> 248.7796 | H6: =H5-H4 -> 87.902856 | I6: =I5-I4 -> 1762.4007
A7: Fournisseurs et comptes rattachés | B7: =446879118/10^6 -> 446.87912 | C7: =525347738/10^6 -> 525.34774 | D7: =527510803/10^6 -> 527.5108 | F7: TN (DU BILAN ) | G7: =B17-B18 -> 248.7796 | H7: =C17-C18 -> 87.902856 | I7: =D17-D18 -> 333.14836
A8: Autres dettes | B8: =582847335/10^6 -> 582.84734 | C8: =751468049/10^6 -> 751.46805 | D8: =1524912274/10^6 -> 1524.9123 | F8: DSO | G8: =ROUNDUP(B5/B3*365, 0) -> 136 | H8: =ROUNDUP(C5/C3*365, 0) -> 134 | I8: =ROUNDUP(D5/D3*365, 0) -> 121
A9: Actif circulant | B9: =686391445/10^6 -> 686.39144 | C9: =958187690/10^6 -> 958.18769 | D9: =1663947368/10^6 -> 1663.9474 | F9: DIO | G9: =ROUNDUP(B4/B11*365, 0) -> 43 | H9: =ROUNDUP(C4/C11*365, 0) -> 39 | I9: =ROUNDUP(D4/D11*365, 0) -> 45
A10: Passif circulant | B10: =1029726453/10^6 -> 1029.7265 | C10: =1276815787/10^6 -> 1276.8158 | D10: =2052423077/10^6 -> 2052.4231 | F10: EBITDA | G10: =B21+B22 -> 282.87608 | H10: =C21+C22 -> 510.81767 | I10: =D21+D22 -> 838.82059
A11: Achats et autres charges externes | B11: =490446675/10^6 -> 490.44668 | C11: =944664048/10^6 -> 944.66405 | D11: =1454241960/10^6 -> 1454.242 | F11: Marge d EBITDA | G11: =G10/B3 -> 0.27336888 | H11: =H10/C3 -> 0.26781831 | I11: =I10/D3 -> 0.2839572
A12: Capitaux propres de l’ensemble consolidé | B12: =1277964945/10^6 -> 1277.9649 | C12: =1425567536/10^6 -> 1425.5675 | D12: =2638508203/10^6 -> 2638.5082 | F12: Taux de conversion | G12: =B19/G10 -> 1.6413714 | H12: =C19/H10 -> 0.46861321 | I12: =D19/I10 -> 0.20189412
A13: Dettes de financement | B13: =433581211/10^6 -> 433.58121 | C13: =1067190582/10^6 -> 1067.1906 | D13: =1434195198/10^6 -> 1434.1952 | F13: Capex | G13: =B23+B24 -> 836.95352 | H13: =C23+C24 -> 1018.8839 | I13: =D23 -> 2604.8103
A14: Provisions pour risques et charges | B14: =708367/10^6 -> 0.708367 | C14: =669012/10^6 -> 0.669012 | D14: =1428622648/10^6 -> 1428.6226 | F14: Capex/Amortissements | G14: =G13/B22 -> 7.8973334 | H14: =H13/C22 -> 5.5763639 | I14: =I13/D22 -> 8.1511755
A15: Impôts différés passifs | B15: =10545193/10^6 -> 10.545193 | C15: =10853448/10^6 -> 10.853448 | D15: =629658/10^6 -> 0.629658 | F15: Résultat de l’exercice | G15: =87651981/10^6 -> 87.651981 | H15: =174686517/10^6 -> 174.68652 | I15: =314609432 /10^6 -> 314.60943
A16: Actif immobilisé | B16: =1817355128/10^6 -> 1817.3551 | C16: =2735005819/10^6 -> 2735.0058 | D16: =4128030755/10^6 -> 4128.0308
A17: Trésorerie - actif | B17: =530260154/10^6 -> 530.26015 | C17: =206449652/10^6 -> 206.44965 | D17: =575808633/10^6 -> 575.80863
A18: Trésorerie - passif | B18: =281480558/10^6 -> 281.48056 | C18: =118546796/10^6 -> 118.5468 | D18: =242660277/10^6 -> 242.66028
A19: Flux net de Trésorerie généré par l'activité | B19: =464304723/10^6 -> 464.30472 | C19: =239375907/10^6 -> 239.37591 | D19: =169352948/10^6 -> 169.35295
A20: Charges de personnel | B20: =-243905906/10^6 -> -243.90591 | C20: =-423789808/10^6 -> -423.78981 | D20: =-611133188/10^6 -> -611.13319
A21: RÉSULTAT D’EXPLOITATION | B21: =176896828/10^6 -> 176.89683 | C21: =328102925/10^6 -> 328.10293 | D21: =519258058/10^6 -> 519.25806
A22: Dotations d’exploitation, nettes des reprises et TC | B22: =105979256/10^6 -> 105.97926 | C22: =182714744/10^6 -> 182.71474 | D22: =319562536/10^6 -> 319.56254
A23: Acquisition des immobilisations incorporelles | B23: =30846362/10^6 -> 30.846362 | C23: =130259157/10^6 -> 130.25916 | D23: =2604810300/10^6 -> 2604.8103
A24: Acquisition des immobilisations corporelles | B24: =806107158/10^6 -> 806.10716 | C24: =888624749/10^6 -> 888.62475

Sheet pont EBITDA
B1: Valeur | C1: Source
A2: Capacité litière fin 2024 | B2: 3706 | C2: RFA 2024 p.24 | F2: 2022 | G2: 2023 | H2: 2024 | I2: Type | J2: Ref
A3: Lits ouverts en 2024 | B3: 1402 | C3: RFA 2024 p.18-20, somme des 12 | E3: EBITDA reporté | F3: =AKDITAL!G10 -> 282.87608 | G3: =AKDITAL!H10 -> 510.81767 | H3: =AKDITAL!I10 -> 838.82059 | J3: comptes consolidés
A4: Capacité litière fin 2023 | B4: =B2-B3 -> 2304 | E4: Pro forma ouvertures | H4: =B16 -> 80.082988 | I4: Soft | J4: A1
A5: CA 2024 (MMADH) | B5: =AKDITAL!D3 -> 2954.0388 | C5: CPC consolidé | E5: Loyer en année pleine (plancher) | H5: =B17 -> -12.361708 | I5: Soft | J5: A2
A6: CA 2023 (MMADH) | B6: =AKDITAL!C3 -> 1907.3291 | C6: CPC consolidé | E6: Frais de démarrage capitalisés | H6: =-B18 -> -45.8 | I6: Soft | J6: A3
A7: CA 2022 (MMADH) | B7: =AKDITAL!B3 -> 1034.7779 | C7: CPC consolidé | E7: EBITDA normalisé | F7: =F3 -> 282.87608 | G7: =G3 -> 510.81767 | H7: =H3+H4+H5+H6 -> 860.74187
A8: CA par lit mature 2023(MMADH) | B8: =B6/B4 -> 0.82783382 | E8: Marge EBITDA normalisée | F8: =F3/B7 -> 0.27336888 | G8: =G3/B6 -> 0.26781831 | H8: =H7/B5 -> 0.29137799
A9: Coefficient de maturité | B9: 0.6 | C9: hypothèse — voir note
A10: Marge d'EBITDA retenue | B10: 0.23 | C10: hypothèse — voir note
A11: Potentiel annuel | B11: =B3*B8*B9*B10 -> 160.16598
A12: Part déjà réalisée (6/12) | B12: =B11*6/12 -> 80.082988 | C12: hypothèse ouvertures uniformes | E12: Scenario | F12: Ramp-up (%) | G12: Marge EBITDA (%) | H12: Potentiel Annuel Brut (MMAD | I12: Impact Réalisé 6/12 (MMAD) | J12: Ajustement Net (MMAD)
A13: Frais préliminaires | B13: 26.1 | C13: Bilan actif consolidé | E13: Borne Basse | F13: 0.5 | G13: 0.15 | H13: =B3*B8*F13*G13 -> 87.046726 | I13: =H13*6/12 -> 43.523363 | J13: =H13-I13 -> 43.523363
A14: Charges à répartir sur plusieurs exercices | B14: 19.7 | C14: Bilan actif consolidé | E14: Cas Central | F14: 0.6 | G14: 0.18 | H14: =B3*B8*F14*G14 -> 125.34729 | I14: =H14*6/12 -> 62.673643 | J14: =H14-I14 -> 62.673643
A15: Loyer annuel | B15: =385.3*7% -> 26.971 | E15: Borne Haute | F15: 0.7 | G15: 0.22 | H15: =B3*B8*F15*G15 -> 178.73594 | I15: =H15*6/12 -> 89.367972 | J15: =H15-I15 -> 89.367972
A16: Ajustement net(A1) | B16: =B11-B12 -> 80.082988
A17: Ajustement net(A2) | B17: =-B15/12*5.5 -> -12.361708
A18: Ajustement net(A3) | B18: =B13+B14 -> 45.8
A22: Méthode retenue : L'ajustement est modélisé par la capacité litière additionnelle (1 402 lits ouverts en 2024) appliquée à un chiffre d'affaires étalon normatif par lit issu du parc existant 2023.
A23: Cas Central (60 % / 23 %) : Le taux de montée en charge de 60 % traduit la phase de maturité progressive (18 à 24 mois).En isolant les frais de démarrage en ligne séparée (A3 : -45,8 MMAD), la marge d'A1 ne doit plus subir la dégradation liée à ces coûts initiaux (d'où l'abandon des 18 %). Cependant, nous ne retenons pas non plus la marge de croisière du groupe (28,4 %), car les nouveaux établissements ouverts en 2024 restent en phase de montée en puissance (ramp-up) avec un taux d'occupation progressif. Une marge intermédiaire de 23–24 % reflète fidèlement la rentabilité opérationnelle courante de ces sites.
A24: Exclusion de la Marge à 25 % : Une marge de 25 % est écartée car elle est trop proche de la marge de croisière du groupe et néglige le poids des coûts fixes de démarrage.
A25: Traitement du Double Comptage : L'ajustement brut (125,4 MMAD sur 12 mois) est neutralisé de la part déjà enregistrée en 2024 (estimée à 6/12ème sous l'hypothèse d'une ouverture uniforme), soit un ajustement net central de +62,7 MMAD (fourchette de +43,5 à +89,4 MMAD).
A26: Limites : Cet ajustement constitue une estimation d'ordre de grandeur en l'absence de ventilation détaillée par établissement communiquée par le vendeur.
A27: Assiette : prix de cession d'Akdital Immo (385,3 MMAD, tableau de flux). Rendement locatif retenu : 7 %, fourchette de marché 6-8 % pour l'immobilier de santé. Cession au 11/06/2024, soit 6,5 mois de charge en 2024, prorata linéaire. Le contrôle de vraisemblance montre que cette assiette sous-estime le parc concerné : l'ajustement est un plancher. Le montant exact des loyers et le détail des baux sont demandés au vendeur.
A28: Ajustement A3:L'EBITDA étant un agrégat calculé avant dotations aux amortissements, il convient d'isoler l'impact total sur la trésorerie/rentabilité brute de la période. Si ces coûts avaient été passés en charges (selon une norme comptable standard) au lieu d'être capitalisés en non-valeurs, l'EBITDA aurait été directement imputé de 45,8 MMAD. Retraiter le montant net (22,6 MMAD) reviendrait à réintégrer indirectement un impact d'amortissement, ce qui dénature le concept d'EBITDA.
